into_dbus_python/__init__.py
into_dbus_python/_errors.py
into_dbus_python/_signature.py
into_dbus_python/_version.py
into_dbus_python/_xformer.py
into_dbus_python-0.8.2.dist-info/LICENSE
into_dbus_python-0.8.2.dist-info/METADATA
into_dbus_python-0.8.2.dist-info/WHEEL
into_dbus_python-0.8.2.dist-info/top_level.txt
into_dbus_python-0.8.2.dist-info/RECORD
