Metadata-Version: 2.1
Name: into-dbus-python
Version: 0.8.2
Summary: "transforms values into properly wrapped dbus-python objects"
Home-page: https://github.com/stratis-storage/into-dbus-python
Author: Anne Mulhern
Author-email: amulhern@redhat.com
License: Apache-2.0
Platform: Linux
Classifier: Development Status :: 4 - Beta
Classifier: Intended Audience :: Developers
Classifier: License :: OSI Approved :: Apache Software License
Classifier: Operating System :: POSIX :: Linux
Classifier: Programming Language :: Python
Classifier: Programming Language :: Python :: 3
Classifier: Programming Language :: Python :: Implementation :: CPython
Classifier: Programming Language :: Python :: Implementation :: PyPy
Classifier: Topic :: Software Development :: Libraries
Classifier: Topic :: Software Development :: Libraries :: Python Modules
License-File: LICENSE
Requires-Dist: dbus-signature-pyparsing
Requires-Dist: dbus-python (>=1.2.10)
